pyosmptparser-2.2.0.dist-info/METADATA
pyosmptparser-2.2.0.dist-info/WHEEL
pyosmptparser/__init__.py
pyosmptparser/pyosmptparser.cpython-312-x86_64-linux-gnu.so
pyosmptparser-2.2.0.dist-info/RECORD
