Metadata-Version: 2.3
Name: pyosmptparser
Version: 2.2.0
Author: Julian Perelli <jperelli@gmail.com>
Author-email: Julian Perelli <jperelli@gmail.com>
License: AGPL-3.0-or-later
